base32_crockford.py
base32_crockford-0.3.0.dist-info/top_level.txt
base32_crockford-0.3.0.dist-info/RECORD
base32_crockford-0.3.0.dist-info/METADATA
base32_crockford-0.3.0.dist-info/WHEEL
base32_crockford-0.3.0.dist-info/metadata.json
base32_crockford-0.3.0.dist-info/DESCRIPTION.rst
