Metadata-Version: 2.0
Name: base32-crockford
Version: 0.3.0
Summary: A Python implementation of Douglas Crockford's base32 encoding scheme
Home-page: https://github.com/jbittel/base32-crockford
Author: Jason Bittel
Author-email: jason.bittel@gmail.com
License: BSD
Download-URL: https://pypi.python.org/pypi/base32-crockford/
Platform: UNKNOWN
Classifier: Development Status :: 4 - Beta
Classifier: Intended Audience :: Developers
Classifier: License :: OSI Approved :: BSD License
Classifier: Operating System :: OS Independent
Classifier: Programming Language :: Python
Classifier: Programming Language :: Python :: 2
Classifier: Programming Language :: Python :: 2.6
Classifier: Programming Language :: Python :: 2.7
Classifier: Programming Language :: Python :: 3
Classifier: Programming Language :: Python :: 3.3
Classifier: Programming Language :: Python :: 3.4
Classifier: Topic :: Software Development :: Libraries :: Python Modules
Classifier: Topic :: Utilities
